p3/__init__.py
p3/base.py
p3/pipeline.py
p3/settings.py
p3/utility.py
p3/version
p3/templates/MNI152.nii.gz
p3/workflows/__init__.py
p3/workflows/p3_alignanattoatlas/__init__.py
p3/workflows/p3_alignanattoatlas/custom.py
p3/workflows/p3_alignanattoatlas/nodedefs.py
p3/workflows/p3_alignanattoatlas/workflow.py
p3/workflows/p3_alignfunctoanat/__init__.py
p3/workflows/p3_alignfunctoanat/custom.py
p3/workflows/p3_alignfunctoanat/nodedefs.py
p3/workflows/p3_alignfunctoanat/workflow.py
p3/workflows/p3_alignfunctoatlas/__init__.py
p3/workflows/p3_alignfunctoatlas/custom.py
p3/workflows/p3_alignfunctoatlas/nodedefs.py
p3/workflows/p3_alignfunctoatlas/workflow.py
p3/workflows/p3_bidsselector/__init__.py
p3/workflows/p3_bidsselector/custom.py
p3/workflows/p3_bidsselector/nodedefs.py
p3/workflows/p3_bidsselector/workflow.py
p3/workflows/p3_create_fs_masks/__init__.py
p3/workflows/p3_create_fs_masks/custom.py
p3/workflows/p3_create_fs_masks/nodedefs.py
p3/workflows/p3_create_fs_masks/workflow.py
p3/workflows/p3_fieldmapcorrection/__init__.py
p3/workflows/p3_fieldmapcorrection/custom.py
p3/workflows/p3_fieldmapcorrection/nodedefs.py
p3/workflows/p3_fieldmapcorrection/workflow.py
p3/workflows/p3_freesurfer/__init__.py
p3/workflows/p3_freesurfer/custom.py
p3/workflows/p3_freesurfer/nodedefs.py
p3/workflows/p3_freesurfer/workflow.py
p3/workflows/p3_skullstrip/__init__.py
p3/workflows/p3_skullstrip/nodedefs.py
p3/workflows/p3_skullstrip/workflow.py
p3/workflows/p3_stcdespikemoco/__init__.py
p3/workflows/p3_stcdespikemoco/custom.py
p3/workflows/p3_stcdespikemoco/nodedefs.py
p3/workflows/p3_stcdespikemoco/workflow.py
p3/workflows/workflow_template/__init__.py
p3/workflows/workflow_template/custom.py
p3/workflows/workflow_template/nodedefs.py
p3/workflows/workflow_template/workflow.py
p3proc-0.1.2.data/scripts/p3proc
p3proc-0.1.2.dist-info/METADATA
p3proc-0.1.2.dist-info/RECORD
p3proc-0.1.2.dist-info/WHEEL
p3proc-0.1.2.dist-info/top_level.txt
