Metadata-Version: 2.1
Name: p3proc
Version: 0.1.2
Summary: The p3 fmri processing pipeline
Home-page: https://github.com/p3proc/p3
Author: Andrew Van
Author-email: vanandrew@wustl.edu
License: UNKNOWN
Platform: UNKNOWN
Classifier: Programming Language :: Python :: 3
Classifier: License :: OSI Approved :: MIT License
Classifier: Operating System :: OS Independent
Requires-Dist: nipype (>=1.1.1)
Requires-Dist: duecredit (>=0.2.2)
Requires-Dist: pybids (>=0.6.3)
Requires-Dist: pandas (>=0.23.1)
Requires-Dist: patsy (>=0.5.0)
Requires-Dist: numpy (==1.14.5)
Requires-Dist: xvfbwrapper (>=0.2.9)
